helsing/scm/__init__.py
helsing/scm/__main__.py
helsing/scm/py.typed
helsing/scm/resources/__init__.py
helsing/scm/resources/v1alpha/AwsAccount.py
helsing/scm/resources/v1alpha/TerraformWorkspace.py
helsing/scm/resources/v1alpha/__init__.py
helsing/scm/tfcodegen/__init__.py
helsing/scm/tfcodegen/aws/__init__.py
helsing/scm/tfcodegen/aws/account_service.py
helsing/scm/tfcodegen/aws/create_account.py
helsing/scm/tfcodegen/aws/settings.py
helsing/scm/tfcodegen/tfe/__init__.py
helsing/scm/tfcodegen/tfe/account_service.py
helsing/scm/tfcodegen/tfe/create_workspace.py
helsing/scm/tfcodegen/tfe/settings.py
helsing/scm/utils/develop.py
helsing/scm/utils/templating.py
helsing/scm/utils/types.py
helsing_scm-0.2.1.dist-info/LICENSE
helsing_scm-0.2.1.dist-info/METADATA
helsing_scm-0.2.1.dist-info/WHEEL
helsing_scm-0.2.1.dist-info/entry_points.txt
helsing_scm-0.2.1.dist-info/RECORD
