Metadata-Version: 2.1
Name: helsing-scm
Version: 0.2.1
Summary: 
License: MIT
Author: Niklas Rosenstein
Author-email: rosensteinniklas@gmail.com
Requires-Python: >=3.10,<4.0
Classifier: License :: OSI Approved :: MIT License
Classifier: Programming Language :: Python :: 3
Classifier: Programming Language :: Python :: 3.10
Classifier: Programming Language :: Python :: 3.11
Requires-Dist: databind.json (>=4.2.5,<5.0.0)
Requires-Dist: frozendict (>=2.3.8,<3.0.0)
Requires-Dist: mako (>=1.2.4,<2.0.0)
Requires-Dist: python-adjudicator (>=0.1.1,<0.2.0)
Requires-Dist: python-equilibrium (>=0.4.0,<0.5.0)
Requires-Dist: pyyaml (>=6.0,<7.0)
Requires-Dist: rich (>=13.3.5,<14.0.0)
Requires-Dist: typer (>=0.9.0,<0.10.0)
